tlogger-0.2.2.dist-info/DESCRIPTION.rst
tlogger-0.2.2.dist-info/METADATA
tlogger-0.2.2.dist-info/top_level.txt
tlogger-0.2.2.dist-info/metadata.json
tlogger-0.2.2.dist-info/WHEEL
tlogger-0.2.2.dist-info/pbr.json
tlogger-0.2.2.dist-info/RECORD
tlogger/logger.py
tlogger/__init__.py
tlogger/action_stack.py
tlogger/compat.py
tlogger/utils.py
tlogger/constants.py
tlogger/actions.py
tlogger/events.py
tlogger/serializers.py
tlogger/action_binder.py
tlogger/formatter.py
tlogger/proxies.py
tlogger/decorators.py
tlogger/django/__init__.py
tlogger/django/middleware.py
