Metadata-Version: 2.0
Name: tlogger
Version: 0.2.2
Summary: Syntax sugar for logging.
Home-page: https://github.com/oxyum/python-tlogger
Author: Ivan Fedorov
Author-email: oxyum@oxyum.ru
License: MIT
Keywords: logging
Platform: UNKNOWN
Classifier: Development Status :: 4 - Beta
Classifier: Intended Audience :: Developers
Classifier: Topic :: Software Development
Classifier: Topic :: System :: Logging
Classifier: License :: OSI Approved :: MIT License
Classifier: Operating System :: OS Independent
Classifier: Programming Language :: Python
Classifier: Programming Language :: Python :: 2
Classifier: Programming Language :: Python :: 2.7
Classifier: Programming Language :: Python :: 3
Classifier: Programming Language :: Python :: 3.2
Classifier: Programming Language :: Python :: 3.4
Classifier: Framework :: Django
Classifier: Framework :: Django :: 1.7
Classifier: Framework :: Django :: 1.8
Requires-Dist: enum34
